ibancom/__init__.py
ibancom/ibancom.py
ibancom-0.6.2.dist-info/AUTHORS.rst
ibancom-0.6.2.dist-info/LICENSE
ibancom-0.6.2.dist-info/METADATA
ibancom-0.6.2.dist-info/WHEEL
ibancom-0.6.2.dist-info/entry_points.txt
ibancom-0.6.2.dist-info/top_level.txt
ibancom-0.6.2.dist-info/RECORD
