Metadata-Version: 2.1
Name: ibancom
Version: 0.6.2
Summary: Python client for IBAN.com service
Home-page: https://github.com/RegioHelden/ibancom
Author: RegioHelden GmbH
Author-email: entwicklung@regiohelden.de
License: MIT license
Keywords: ibancom
Platform: UNKNOWN
Classifier: Development Status :: 2 - Pre-Alpha
Classifier: Intended Audience :: Developers
Classifier: License :: OSI Approved :: MIT License
Classifier: Natural Language :: English
Classifier: Programming Language :: Python :: 3
Classifier: Programming Language :: Python :: 3.6
Classifier: Programming Language :: Python :: 3.7
Classifier: Programming Language :: Python :: 3.8
Requires-Dist: requests (>=2.21.0)
